sequential/JK/jk_posedge.v
`timescale 10ns / 1ns

module jkff_posedge(
    input [1:0] jk,
    input clk,
    output reg q, qbar
);

    always @(posedge clk)
        begin
            case(jk)
                2'b00:
                    begin
                        q = q;
                        qbar = qbar;
                    end
                2'b01:
                    begin
                        q = 0;
                        qbar = 1;
                    end

                2'b10:
                    begin
                        q = 1;
                        qbar = 0;
                    end

                2'b11:
                    begin
                        q = ~q;
                        qbar = ~qbar;
                    end

                default:
                    begin
                        q = 0;
                        qbar = 0;
                    end
            endcase
        end
endmodule

module jkff_posedge_tb;

    reg [1:0] jk;
    reg clk;
    wire q, qbar;

    jkff_posedge uut(.jk(jk), .clk(clk), .q(q), .qbar(qbar));

    initial
    begin
        $dumpfile("jkff_posedge.vcd");
        $dumpvars(0, jkff_posedge_tb);

        jk = 2'b00;
        #10;

        jk = 2'b10;
        #30;

        jk = 2'b01;
        #20;

        jk = 2'b10;
        #30;

        jk = 2'b00;
        #30;

        jk = 2'b11;
        #10;
    end

    initial
    begin
        clk = 0;
        repeat(15)
            begin
                clk = ~clk;
                #10;
            end
    end

    initial
    $monitor("jk = %b, q = %b, qbar = %b\n", jk, q, qbar);
endmodule

sequential/JK/jkff_posedge.vcd
$date
	Thu Nov 21 21:54:12 2019
$end
$version
	Icarus Verilog
$end
$timescale
	1ns
$end
$scope module jkff_posedge_tb $end
$var wire 1 ! qbar $end
$var wire 1 " q $end
$var reg 1 # clk $end
$var reg 2 $ jk [1:0] $end
$scope module uut $end
$var wire 1 # clk $end
$var wire 2 % jk [1:0] $end
$var reg 1 " q $end
$var reg 1 ! qbar $end
$upscope $end
$upscope $end
$enddefinitions $end
#0
$dumpvars
b0 %
b0 $
1#
x"
x!
$end
#100
0#
b10 $
b10 %
#200
0!
1"
1#
#300
0#
#400
1!
0"
1#
b1 $
b1 %
#500
0#
#600
0!
1"
1#
b10 $
b10 %
#700
0#
#800
1#
#900
0#
b0 $
b0 %
#1000
1#
#1100
0#
#1200
1!
0"
1#
b11 $
b11 %
#1300
0#
#1400
0!
1"
1#
