sequential/mod6Counter/mod6Counter.v
`timescale 10ns / 1ns

module mod6Counter(
    input clk,
    output reg [3:1] qOut
);
    reg d3, d2, d1;

    initial
    begin
       qOut = 0;
       d3 = 0;
       d2 = 0;
       d1 = 0;
    end

    always @(posedge clk)
        begin
            qOut[3] = d3;
            qOut[2] = d2;
            qOut[1] = d1;

            d3 = (qOut[3] & ~qOut[2]) | (~qOut[3] & qOut[2] & qOut[1]);
            d2 = (qOut[1] & ~qOut[2]) | (~qOut[3] & qOut[2] & ~qOut[1]);
            d1 = ~qOut[1] & (~qOut[2] | ~qOut[3]);
        end
endmodule

module mod6Counter_tb;

    // reg d3, d2, d1;
    reg clk;
    wire [3:1] q;

    mod6Counter uut(.clk(clk), .qOut(q));

    initial
    begin
        clk = 1;
        $dumpfile("mod6Counter.vcd");
        $dumpvars(0, mod6Counter_tb);
        $monitor("count = %b\n", q);

        repeat(50)
        begin
            clk = ~clk;
            #10;
        end
    end
endmodule

sequential/mod6Counter/mod6Counter.vcd
$date
	Fri Nov 22 01:37:53 2019
$end
$version
	Icarus Verilog
$end
$timescale
	1ns
$end
$scope module mod6Counter_tb $end
$var wire 3 ! q [3:1] $end
$var reg 1 " clk $end
$scope module uut $end
$var wire 1 " clk $end
$var reg 1 # d1 $end
$var reg 1 $ d2 $end
$var reg 1 % d3 $end
$var reg 3 & qOut [3:1] $end
$upscope $end
$upscope $end
$enddefinitions $end
#0
$dumpvars
b0 &
0%
0$
1#
0"
b0 !
$end
#100
0#
1$
b1 !
b1 &
1"
#200
0"
#300
1#
b10 !
b10 &
1"
#400
0"
#500
0#
0$
1%
b11 !
b11 &
1"
#600
0"
#700
1#
b100 !
b100 &
1"
#800
0"
#900
0#
1$
b101 !
b101 &
1"
#1000
0"
#1100
0$
0%
b110 !
b110 &
1"
#1200
0"
#1300
1#
b0 !
b0 &
1"
#1400
0"
#1500
0#
1$
b1 !
b1 &
1"
#1600
0"
#1700
1#
b10 !
b10 &
1"
#1800
0"
#1900
0#
0$
1%
b11 !
b11 &
1"
#2000
0"
#2100
1#
b100 !
b100 &
1"
#2200
0"
#2300
0#
1$
b101 !
b101 &
1"
#2400
0"
#2500
0$
0%
b110 !
b110 &
1"
#2600
0"
#2700
1#
b0 !
b0 &
1"
#2800
0"
#2900
0#
1$
b1 !
b1 &
1"
#3000
0"
#3100
1#
b10 !
b10 &
1"
#3200
0"
#3300
0#
0$
1%
b11 !
b11 &
1"
#3400
0"
#3500
1#
b100 !
b100 &
1"
#3600
0"
#3700
0#
1$
b101 !
b101 &
1"
#3800
0"
#3900
0$
0%
b110 !
b110 &
1"
#4000
0"
#4100
1#
b0 !
b0 &
1"
#4200
0"
#4300
0#
1$
b1 !
b1 &
1"
#4400
0"
#4500
1#
b10 !
b10 &
1"
#4600
0"
#4700
0#
0$
1%
b11 !
b11 &
1"
#4800
0"
#4900
1#
b100 !
b100 &
1"
